microprobe/__init__.py
microprobe/exceptions.py
microprobe/property.py
microprobe/code/__init__.py
microprobe/code/address.py
microprobe/code/bbl.py
microprobe/code/benchmark.py
microprobe/code/cfg.py
microprobe/code/context.py
microprobe/code/ins.py
microprobe/code/var.py
microprobe/code/wrapper.py
microprobe/driver/__init__.py
microprobe/driver/genetic.py
microprobe/driver/guided.py
microprobe/model/__init__.py
microprobe/model/memory.py
microprobe/passes/__init__.py
microprobe/passes/address/__init__.py
microprobe/passes/branch/__init__.py
microprobe/passes/dat/__init__.py
microprobe/passes/decimal/__init__.py
microprobe/passes/float/__init__.py
microprobe/passes/ilp/__init__.py
microprobe/passes/initialization/__init__.py
microprobe/passes/instruction/__init__.py
microprobe/passes/memory/__init__.py
microprobe/passes/register/__init__.py
microprobe/passes/structure/__init__.py
microprobe/passes/switch/__init__.py
microprobe/passes/symbol/__init__.py
microprobe/passes/variable/__init__.py
microprobe/schemas/__init__.py
microprobe/target/__init__.py
microprobe/target/env/__init__.py
microprobe/target/isa/__init__.py
microprobe/target/isa/comparator.py
microprobe/target/isa/dat.py
microprobe/target/isa/generator.py
microprobe/target/isa/instruction.py
microprobe/target/isa/instruction_field.py
microprobe/target/isa/instruction_format.py
microprobe/target/isa/operand.py
microprobe/target/isa/register.py
microprobe/target/isa/register_type.py
microprobe/target/isa/schemas/__init__.py
microprobe/target/uarch/__init__.py
microprobe/target/uarch/cache.py
microprobe/target/uarch/element.py
microprobe/target/uarch/element_type.py
microprobe/target/uarch/schemas/__init__.py
microprobe/utils/__init__.py
microprobe/utils/asm.py
microprobe/utils/bin.py
microprobe/utils/cache.py
microprobe/utils/cmdline.py
microprobe/utils/config.py
microprobe/utils/distrib.py
microprobe/utils/ieee.py
microprobe/utils/imp.py
microprobe/utils/info.py
microprobe/utils/logger.py
microprobe_all-0.5.20250911152917.dist-info/licenses/LICENSE
microprobe_all-0.5.20250911152917.dist-info/METADATA
microprobe_all-0.5.20250911152917.dist-info/WHEEL
microprobe_all-0.5.20250911152917.dist-info/top_level.txt
microprobe_all-0.5.20250911152917.dist-info/RECORD
